[
  {
    "name": "\"Dutch\" Vander",
    "subname": "Y-wing Squadron",
    "unique": true,
    "faction": "Rebel Alliance",
    "speed": 3,
    "hull": 6,
    "__comment": "dice array is [red, blue, black] counts",
    "squadron-attack": [0, 3, 0],
    "attack": [0, 0, 1],
    "text":
      "When a squadron you attack suffers at least 1 damage, you may toggle its activation slider to the activated side. If it was already activated, it suffers 1 additional damage instead.",
    "keywords": ["Bomber", "Heavy"],
    "defense-tokens": ["Brace", "Brace"],
    "points": 16,
    "squadron-image": "squadron/rebel-alliance/y-wing-squadron.png",
    "image": "squadron-card/rebel-alliance/dutch-vander.png"
  }
]
